cohesive/__init__.py
cohesive/base.py
cohesive/cohesive.py
cohesive/encoder.py
cohesive/utils.py
cohesive-0.1.6.dist-info/LICENSE
cohesive-0.1.6.dist-info/METADATA
cohesive-0.1.6.dist-info/WHEEL
cohesive-0.1.6.dist-info/RECORD
