Metadata-Version: 2.1
Name: cohesive
Version: 0.1.6
Summary: Use sentence embeddings to create naturally coherent segments of text akin to paragraphs.
Home-page: https://github.com/matthewdutton1983/cohesive
License: Apache-2.0
Author: Matthew Dutton
Author-email: matthewdutton1983@hotmail.co.uk
Requires-Python: >=3.8,<4.0
Classifier: License :: OSI Approved :: Apache Software License
Classifier: Programming Language :: Python :: 3
Classifier: Programming Language :: Python :: 3.8
Classifier: Programming Language :: Python :: 3.9
Classifier: Programming Language :: Python :: 3.10
Classifier: Programming Language :: Python :: 3.11
Classifier: Programming Language :: Python :: 3.12
Requires-Dist: networkx (>=2.6.3,<3.0.0)
Requires-Dist: numpy (>=1.21.2,<2.0.0)
Requires-Dist: python-louvain (>=0.15,<0.16)
Requires-Dist: scikit-learn (>=1.3.2,<2.0.0)
Requires-Dist: scipy (>=1.11.4,<2.0.0)
Requires-Dist: sentence-transformers (>=2.1.0,<3.0.0)
Project-URL: Repository, https://github.com/matthewdutton1983/cohesive
